pymessagelib/__init__.py
pymessagelib/_exceptions.py
pymessagelib/dependency_graph.py
pymessagelib/field.py
pymessagelib/message.py
pymessagelib/message_builder.py
pymessagelib-0.2.7.dist-info/LICENSE
pymessagelib-0.2.7.dist-info/METADATA
pymessagelib-0.2.7.dist-info/WHEEL
pymessagelib-0.2.7.dist-info/top_level.txt
pymessagelib-0.2.7.dist-info/RECORD
